mle_logging/__init__.py
mle_logging/_version.py
mle_logging/meta_log.py
mle_logging/mle_logger.py
mle_logging/load/__init__.py
mle_logging/load/load_log.py
mle_logging/load/load_model.py
mle_logging/merge/__init__.py
mle_logging/merge/aggregate.py
mle_logging/merge/merge_hdf5.py
mle_logging/merge/merge_logs.py
mle_logging/save/__init__.py
mle_logging/save/extra_log.py
mle_logging/save/figure_log.py
mle_logging/save/model_log.py
mle_logging/save/stats_log.py
mle_logging/save/tboard_log.py
mle_logging/save/wandb_log.py
mle_logging/utils/__init__.py
mle_logging/utils/comms.py
mle_logging/utils/helpers.py
mle_logging-0.0.6.dist-info/LICENSE
mle_logging-0.0.6.dist-info/METADATA
mle_logging-0.0.6.dist-info/WHEEL
mle_logging-0.0.6.dist-info/top_level.txt
mle_logging-0.0.6.dist-info/RECORD
