Metadata-Version: 2.1
Name: mle_logging
Version: 0.0.6
Summary: Machine Learning Experiment Logging
Home-page: https://github.com/mle-infrastructure/mle-logging
Download-URL: https://github.com/mle-infrastructure/mle-logging/archive/v0.0.6.tar.gz
Author: Robert Tjarko Lange
Author-email: robertlange0@gmail.com
Platform: any
Classifier: Programming Language :: Python :: 3.6
Classifier: Programming Language :: Python :: 3.7
Classifier: Programming Language :: Python :: 3.8
Classifier: Programming Language :: Python :: 3.9
Classifier: License :: OSI Approved :: MIT License
Classifier: Operating System :: OS Independent
Classifier: Topic :: Scientific/Engineering :: Artificial Intelligence
Requires-Python: >=3.6
License-File: LICENSE
Requires-Dist: commentjson
Requires-Dist: pyyaml>=5.1
Requires-Dist: numpy
Requires-Dist: h5py
Requires-Dist: dotmap
Requires-Dist: rich
Requires-Dist: pandas
Requires-Dist: wandb
Requires-Dist: pickle5; python_version < "3.8"
Provides-Extra: examples
Requires-Dist: torch; extra == "examples"
Requires-Dist: matplotlib; extra == "examples"
Requires-Dist: seaborn; extra == "examples"
